{
  "id": "0818",
  "character": "壟",
  "sourceUrl": "https://www.edbchinese.hk/lexlist_ch/result.jsp?id=0818&sortBy=ks&jpC=lshk",
  "radical": "土",
  "strokeCount": 19,
  "jyutping": "",
  "pinyin": "",
  "strokeOrderImages": [
    "https://www.edbchinese.hk/EmbziciwebRes/stkdemo_js/0001-1000/0818.html?lang=ch"
  ],
  "strokeVectors": [
    {
      "strokeNumber": 1,
      "segment": 1,
      "frame": 24,
      "pathData": "AhiDNQh+jShhkCQgShWGWBsQCEAtBiA4QBZG6jYAAQhlAAinhhg",
      "transform": {
        "x": 364.7,
        "y": 110.3
      },
      "color": "#000000"
    },
    {
      "strokeNumber": 1,
      "segment": 2,
      "frame": 27,
      "pathData": "ACaHeQl2lejepMQgShWGXBsQGgCNBHD2QAqEwiTC1QgxBBg5AAQghAAgkgVg",
      "transform": {
        "x": 376.7,
        "y": 130
      },
      "color": "#000000"
    },
    {
      "strokeNumber": 2,
      "segment": 1,
      "frame": 48,
      "pathData": "AnmBeQjjiND5ghQGBgcFcgtQJ8AupeDzQjMASidAAQkhAAiHg8g",
      "transform": {
        "x": 272.9,
        "y": 206.1
      },
      "color": "#000000"
    },
    {
      "strokeNumber": 2,
      "segment": 2,
      "frame": 51,
      "pathData": "AwkDLQjjiND4ghQRAhQMcjUQKPAnqdE7QoxBsogAvQjMASieAAQkhAAiHg9g",
      "transform": {
        "x": 330.3,
        "y": 195.2
      },
      "color": "#000000"
    },
    {
      "strokeNumber": 2,
      "segment": 3,
      "frame": 54,
      "pathData": "A1xEWQjjiOD5ggQVnhnOPk6QDjhIDyCNQDtCRkSBDQvuEPu8BSQjMASieAAQkhAAiHg9g",
      "transform": {
        "x": 363.6,
        "y": 187.7
      },
      "color": "#000000"
    },
    {
      "strokeNumber": 3,
      "segment": 1,
      "frame": 72,
      "pathData": "AhIDCQh8jLiFkGQgLhAEaBAQDhBKCbBqQAtGLi3AAQhhAAifhug",
      "transform": {
        "x": 300.7,
        "y": 266.5
      },
      "color": "#000000"
    },
    {
      "strokeNumber": 3,
      "segment": 2,
      "frame": 75,
      "pathData": "ABYGRQj5kmktpMQgLhAEaBAQGqCKCrEBQBTC1gmDgQhEDDhsAAQhSAAhphxg",
      "transform": {
        "x": 314,
        "y": 287.5
      },
      "color": "#000000"
    },
    {
      "strokeNumber": 4,
      "segment": 1,
      "frame": 96,
      "pathData": "AknB6QAplNhQinQAUi4H4EOQC7Bhg1CBQhQCNhNCFQjyD2h2AAQiIAAAilMg",
      "transform": {
        "x": 458.8,
        "y": 238.1
      },
      "color": "#000000"
    },
    {
      "strokeNumber": 4,
      "segment": 2,
      "frame": 99,
      "pathData": "AmUJ9QFPv+ijlSQAVi4H4EOQC7Bhg2CBQlQJXkoG8QihCngxAAQgwAAA8iig",
      "transform": {
        "x": 448.5,
        "y": 272.6
      },
      "color": "#000000"
    },
    {
      "strokeNumber": 5,
      "segment": 1,
      "frame": 120,
      "pathData": "AkwEGQk6hKjLiaQh9hiD/gnQI1hOI8hcQMSgCq2FOQj4BDj1BIQifBMhvAAQgrAAgkgMg",
      "transform": {
        "x": 154.4,
        "y": 402.2
      },
      "color": "#000000"
    },
    {
      "strokeNumber": 5,
      "segment": 2,
      "frame": 123,
      "pathData": "AyoGvQk6hLjKiZQh+hjD/goQXQjMYEktQJQAuo6DdQyfDQxqFMQifBMhwAAQgrAAgkgLg",
      "transform": {
        "x": 243.1,
        "y": 385.3
      },
      "color": "#000000"
    },
    {
      "strokeNumber": 5,
      "segment": 3,
      "frame": 126,
      "pathData": "A86IcQk6hLjKiZQh+hjD/goUAemgENAgCgG0QGTg+CuCZQCuCslFATQh1AAkxAlQ6aDe4xHSQifBMhvAAQgsAAgkgLg",
      "transform": {
        "x": 308.9,
        "y": 374.4
      },
      "color": "#000000"
    },
    {
      "strokeNumber": 6,
      "segment": 1,
      "frame": 144,
      "pathData": "AhaDcQgLnGiLi7QiAh+DmgDQE+gDBSB0QAyBYgyD4QADBwAAByQhfGqheAAQhTAAhTlLg",
      "transform": {
        "x": 285.7,
        "y": 485.9
      },
      "color": "#000000"
    },
    {
      "strokeNumber": 6,
      "segment": 2,
      "frame": 147,
      "pathData": "AiIIFQAokYAHlSQgEnxiTjGQiAh+DmgDQE+gDBSB0QAyBYgyD4QAOHogoIGQjEGMhcAAQhfAAALmZg",
      "transform": {
        "x": 285.7,
        "y": 523.4
      },
      "color": "#000000"
    },
    {
      "strokeNumber": 6,
      "segment": 3,
      "frame": 150,
      "pathData": "AjlRcQhzkjBOjKQCunKAPriQgEnxiTjGQiAh+DmgDQE+gDBSB0QAyBYgyD4QAXM+iDOTQhNF8hNB9QgmBggrAAQhKAAhWkag",
      "transform": {
        "x": 284.5,
        "y": 570.6
      },
      "color": "#000000"
    },
    {
      "strokeNumber": 7,
      "segment": 1,
      "frame": 168,
      "pathData": "ApuAEQIDg1HdigQH+AFoIDBQm7A4nRClg",
      "transform": {
        "x": 364,
        "y": 437.9
      },
      "color": "#000000"
    },
    {
      "strokeNumber": 7,
      "segment": 2,
      "frame": 171,
      "pathData": "AH6DdIAAlZQgPiYjngMQpNAbp0DfIhKjPQKzhJJukHQDshkDgB6QCIBFCICKQA7BbiHEUQgYBQgPCAQh5GUhiAAQhjAAhLmWg",
      "transform": {
        "x": 404.9,
        "y": 462.9
      },
      "color": "#000000"
    },
    {
      "strokeNumber": 7,
      "segment": 3,
      "frame": 174,
      "pathData": "AH6JvIAAx+QgPiXjngMQpNAap0DfIhKjOQKzhJJukHQDshkDgB5QCIBFCICKQA7BciHEUQhOEBAWLqQh7GdheABQhdAAhCmXg",
      "transform": {
        "x": 404.9,
        "y": 503.1
      },
      "color": "#000000"
    },
    {
      "strokeNumber": 7,
      "segment": 4,
      "frame": 177,
      "pathData": "AERY2QjlmAjWkXQi1jNCjBBID7BsQCtBMB7hkQCehtgLo/IAA1MQgPiXjngMQpNAap0DfIhKjOQKzhJJukHQDshkDgB5QCIBFCICKQA7BciHEUQhTEQAeM0IAjHoQACL2mZErQhFA/g5AAQhAAAgyhRg",
      "transform": {
        "x": 404.9,
        "y": 567.3
      },
      "color": "#000000"
    },
    {
      "strokeNumber": 8,
      "segment": 1,
      "frame": 192,
      "pathData": "AnSCAIAAiPILIiIQGpAUmJD2QkYAljFAAQihAAhqgYg",
      "transform": {
        "x": 352.3,
        "y": 515.5
      },
      "color": "#000000"
    },
    {
      "strokeNumber": 8,
      "segment": 2,
      "frame": 195,
      "pathData": "AsqCkIAAiQIQEjEQCwgmGhBRIgLB9Qt7DFnEAAQihAAhqgZg",
      "transform": {
        "x": 386.7,
        "y": 511.9
      },
      "color": "#000000"
    },
    {
      "strokeNumber": 9,
      "segment": 1,
      "frame": 216,
      "pathData": "AnMCMQj4h6E+gxIKVh3QJrAkqVDrQkLAejLAAQh5AAhigLg",
      "transform": {
        "x": 346,
        "y": 590.9
      },
      "color": "#000000"
    },
    {
      "strokeNumber": 9,
      "segment": 2,
      "frame": 219,
      "pathData": "AtBC3Qj4h6E+gyIQzjBQEigkD7BKQEbA3pgCTQrJCImsAAQh6AAhigLg",
      "transform": {
        "x": 383.3,
        "y": 586.6
      },
      "color": "#000000"
    },
    {
      "strokeNumber": 10,
      "segment": 1,
      "frame": 240,
      "pathData": "AmICTQkjiPEQg2QFsgiFNhDQIEAuoHDoQjpAZjrAAQhnAAhogFg",
      "transform": {
        "x": 688.3,
        "y": 160.5
      },
      "color": "#000000"
    },
    {
      "strokeNumber": 10,
      "segment": 2,
      "frame": 243,
      "pathData": "AsDDfQkjiPEQg3QKbg9I3ivQDZg3C8CJQCXCDiiAhQhqARjfAqQoUCGofAAQhmAAhngFg",
      "transform": {
        "x": 726.2,
        "y": 152.9
      },
      "color": "#000000"
    },
    {
      "strokeNumber": 11,
      "segment": 1,
      "frame": 264,
      "pathData": "AhpF9QgLoFjIjjQibiqC2gtQFSgaE6DGQAyAwgyC9QgbB7gWCLQiSHph8AAQhPAAhGjJg",
      "transform": {
        "x": 621.5,
        "y": 138.4
      },
      "color": "#000000"
    },
    {
      "strokeNumber": 11,
      "segment": 2,
      "frame": 267,
      "pathData": "Ak3Q8QhZgUh8i+Qg4hzAlhVQALgbAWgYQAihEAOhpQAZjcgQlfQgLoGjIjjQibiqC2gtQFTgaE5DGQAyAwgyC9QhZGgguJdQADDSCzABQC7gCC/gVQJuArqvEaQjtA6jwBnQhcA+hWAAQgPAAgQgBg",
      "transform": {
        "x": 656.3,
        "y": 188.7
      },
      "color": "#000000"
    },
    {
      "strokeNumber": 11,
      "segment": 3,
      "frame": 270,
      "pathData": "AIRNZQAuinjWgFQnlAWn2DXQhtBJhkgNQhZgUh8i+Qg4hyAlhVQALgcAWgYQAihDAOhqQAZjcgQleQgLoHjIjiQibiqC2guQFTgaE6DHQAyAwgyC8QhaGhguJcQADDSC0ABQHqgEIFiLQDqhMElB0QCXBTAjBUQALA+g2BdIgcAsQgtBJgrBQQkPE5iPAAQiSAAgLlKg",
      "transform": {
        "x": 708.7,
        "y": 198.8
      },
      "color": "#000000"
    },
    {
      "strokeNumber": 11,
      "segment": 4,
      "frame": 273,
      "pathData": "AGhTUIBwpwQAuiojWgEQnlAVn2DXQhtBKhkgNQhZgUh8i+Qg4hzAlhVQALgbAWgYQAihEAOhpQAZjbgQlgQgLoGjIjjQibiqC2gtQFTgaE6DGQAyAwgyC9QhaGgguJdQADDSC0ABQHqgFIFiLQDqhLElBzQCXBUAjBUQALA9g2BdIgcAtQjWFbi0H+QjHBjhiAAQiKAAA6jEg",
      "transform": {
        "x": 708.7,
        "y": 223.4
      },
      "color": "#000000"
    },
    {
      "strokeNumber": 12,
      "segment": 1,
      "frame": 288,
      "pathData": "AnehdQFZgeFYg9QLeAYqlEiQlIAwk6AHQl4jwEQgmg",
      "transform": {
        "x": 659.9,
        "y": 372.4
      },
      "color": "#000000"
    },
    {
      "strokeNumber": 12,
      "segment": 2,
      "frame": 291,
      "pathData": "AubgaQJig1JfiXQF1hNEqDYQCSB6iSAzQlpgOliAyQoqB6oDAMQl4jxEQglg",
      "transform": {
        "x": 704.4,
        "y": 365.7
      },
      "color": "#000000"
    },
    {
      "strokeNumber": 13,
      "segment": 1,
      "frame": 312,
      "pathData": "AjcEpIAAmSQAMlzhOikQhoiIDYAiIAZAEIA9ANQD1A5CBDfQBGCHhGEzQgOB2gLB5QiZICh6AAQh0AAhanFg",
      "transform": {
        "x": 599.2,
        "y": 420.2
      },
      "color": "#000000"
    },
    {
      "strokeNumber": 13,
      "segment": 2,
      "frame": 315,
      "pathData": "AjcNaIAA2yQAMlzhOijQhoiJDYAjIAZAEIA9ANQD1A4CBDgQBGCHhGEzQhMJ2AKLTQheGEhvAAQhtAAh+mCg",
      "transform": {
        "x": 599.2,
        "y": 469.6
      },
      "color": "#000000"
    },
    {
      "strokeNumber": 13,
      "segment": 3,
      "frame": 318,
      "pathData": "ADob3Qi7hFirhdQnskwgMvmIAA2yQAMlzhOijQhoiJDYAjIAZAEIA9ANQD2A4CBDgQBGCHhGEzQhfMXAnOnQA8H1IRCIQKyHIsaAAIhKAAg",
      "transform": {
        "x": 640.2,
        "y": 523.5
      },
      "color": "#000000"
    },
    {
      "strokeNumber": 13,
      "segment": 4,
      "frame": 321,
      "pathData": "At4X0QnskxgMvmIAA2xQAMlzhOikQhoiIDYAiIAZAEIA9ANQD2A5CBDfQBGCHhGEzQhfMYAnOmQA8H1ISCIQLbCXKchLQNjDLs2FfQjkAWjXAAQttAAqVllg",
      "transform": {
        "x": 716.4,
        "y": 533.3
      },
      "color": "#000000"
    },
    {
      "strokeNumber": 13,
      "segment": 5,
      "frame": 324,
      "pathData": "A2vX0QnskxgMvmIAA2xQAMlzhOikQhoiIDYAiIAZAEIA9ANQD2A5CBDfQBGCHhGEzQhfMYAnOmQA8H1ISCIQNuC1MRiQQHKh6CRlKQB+j9BZnSQBdjBBKGXQAkHpDrDYQB+C7iNCaQk/Grx1BNQjkAWjXAAQttAAqVllg",
      "transform": {
        "x": 773.1,
        "y": 533.3
      },
      "color": "#000000"
    },
    {
      "strokeNumber": 14,
      "segment": 1,
      "frame": 336,
      "pathData": "AnlCKIAAi1QExgcFthDQJJAYomDVQlIAoknAAIhSgBg",
      "transform": {
        "x": 668.5,
        "y": 455.2
      },
      "color": "#000000"
    },
    {
      "strokeNumber": 14,
      "segment": 2,
      "frame": 339,
      "pathData": "AufDWIAAi3QIkgwLjiyQFLhADiCbQA0BPi9AaIltBBQq2CVo3AAIhRgBg",
      "transform": {
        "x": 712.7,
        "y": 447.7
      },
      "color": "#000000"
    },
    {
      "strokeNumber": 15,
      "segment": 1,
      "frame": 360,
      "pathData": "AnLhFQFUgZEhgwQIxAHoJDfQlQAplNAOg",
      "transform": {
        "x": 661,
        "y": 527.2
      },
      "color": "#000000"
    },
    {
      "strokeNumber": 15,
      "segment": 2,
      "frame": 363,
      "pathData": "Au8ALQJngsHAh4QHBh5ENBZQENBYkXBaQjrA5lDAiQpjBzpaAZg",
      "transform": {
        "x": 710.6,
        "y": 519.1
      },
      "color": "#000000"
    },
    {
      "strokeNumber": 16,
      "segment": 1,
      "frame": 384,
      "pathData": "AobCPIAAi1QGHgoGahBQIaADn3DyQmgAqmBAAIgjgBg",
      "transform": {
        "x": 667.1,
        "y": 591.3
      },
      "color": "#000000"
    },
    {
      "strokeNumber": 16,
      "segment": 2,
      "frame": 387,
      "pathData": "AvEC/IAAi2QJRg8J8h1QF6hAESB1QCxBankBIQs3CQrIAAIgnAAg",
      "transform": {
        "x": 709.5,
        "y": 586.5
      },
      "color": "#000000"
    },
    {
      "strokeNumber": 17,
      "segment": 1,
      "frame": 408,
      "pathData": "AqzBfQjvi+CjACQJzguIwhIQMrBesHEbQlJAblIAQQgoADglAAQkWAAiHh1g",
      "transform": {
        "x": 469.3,
        "y": 808.6
      },
      "color": "#000000"
    },
    {
      "strokeNumber": 17,
      "segment": 2,
      "frame": 411,
      "pathData": "Ax0CoQjvi+CjABQSYhWOyiwQLnBKrQFdQsVBnsWAnQgoACglAAQkVAAiIh0g",
      "transform": {
        "x": 514.2,
        "y": 801.4
      },
      "color": "#000000"
    },
    {
      "strokeNumber": 17,
      "segment": 3,
      "frame": 414,
      "pathData": "A50D4Qjvi/CjACQZEh1SZkdQE/hKEzDAQEeCqmjBfQ1GEA1OBCQgoACglAAQkVAAiIh0g",
      "transform": {
        "x": 565.4,
        "y": 793.3
      },
      "color": "#000000"
    },
    {
      "strokeNumber": 18,
      "segment": 1,
      "frame": 432,
      "pathData": "AjMDMQgOktiKihQhqivBqg1QCIhNGLCBQD1BbgLCVQgZBwgUCcQjJG6iXAAQh+AAhak4g",
      "transform": {
        "x": 553.9,
        "y": 736.7
      },
      "color": "#000000"
    },
    {
      "strokeNumber": 18,
      "segment": 2,
      "frame": 435,
      "pathData": "AiyJ5IgauEQgOkuiKihQhqivBqg1QCIhNGLCBQD1BcgLCVQg7EGgdIAIgRGkQirHLh+AAQhuAAhLljg",
      "transform": {
        "x": 553.9,
        "y": 783.8
      },
      "color": "#000000"
    },
    {
      "strokeNumber": 18,
      "segment": 3,
      "frame": 438,
      "pathData": "AiYSkIg08JQgOkuiKihQhqivBqg1QCIhNGLCBQD1BcgLCVQg7EGgdIBIg4VJQjeDYhnAAQhWAAgGiRg",
      "transform": {
        "x": 553.9,
        "y": 818.4
      },
      "color": "#000000"
    },
    {
      "strokeNumber": 19,
      "segment": 1,
      "frame": 456,
      "pathData": "AqUDwQmzhsieiTQiFipFLADQNQgRQbhAQNtBotJD5Qm6AqmGA3QkaBLjTAAQh3AAhggXg",
      "transform": {
        "x": 345.9,
        "y": 961.9
      },
      "color": "#000000"
    },
    {
      "strokeNumber": 19,
      "segment": 2,
      "frame": 459,
      "pathData": "A95FQQmzhsieiUQiFioFLAEUAbdgAjApDgDwQOaCJt7EeIhYAAQ9yAi0lC6QkbBMjTAAQh3AAhggYg",
      "transform": {
        "x": 471.2,
        "y": 952.3
      },
      "color": "#000000"
    },
    {
      "strokeNumber": 19,
      "segment": 3,
      "frame": 462,
      "pathData": "EgtrAGdQm0hsieiUQiEioFLADUAiCgArA2+gFmQFFhDEoBoQFvCEChC/QBuCgk9AmIoOgJI76AAQ9wAi0nC7QkbBLjTAAQh2AAhggXg",
      "transform": {
        "x": 572.3,
        "y": 944.6
      },
      "color": "#000000"
    }
  ],
  "inLexicalListsHK": false,
  "stage1Words": [],
  "stage2Words": [],
  "fourCharacterPhrases": [],
  "classicalPhrases": [],
  "multiCharacterIdioms": [],
  "properNouns": [],
  "transliteratedWords": []
}