{
  "id": "3987",
  "character": "跼",
  "sourceUrl": "https://www.edbchinese.hk/lexlist_ch/result.jsp?id=3987&sortBy=ks&jpC=lshk",
  "radical": "足",
  "strokeCount": 14,
  "jyutping": "",
  "pinyin": "",
  "strokeOrderImages": [
    "https://www.edbchinese.hk/EmbziciwebRes/stkdemo_js/3001-4000/3987.html?lang=ch"
  ],
  "strokeVectors": [
    {
      "strokeNumber": 1,
      "segment": 1,
      "frame": 24,
      "pathData": "AgXF8IgOhvQg/oEjSisQjTirEyATQExASCBBmQCABlAPFQQATCJAQCFQh2E+h2AAQhdAAhbjCg",
      "transform": {
        "x": 162.2,
        "y": 298.2
      },
      "color": "#000000"
    },
    {
      "strokeNumber": 1,
      "segment": 2,
      "frame": 27,
      "pathData": "ABULgQhdmlhBn/Qg/oFjSisQjTirEyATQExASCBBmQCABlAPFQQBRJMAcILQgBFviAAlQgOAFgOAAQhvAAhSkwg",
      "transform": {
        "x": 165.9,
        "y": 344.8
      },
      "color": "#000000"
    },
    {
      "strokeNumber": 2,
      "segment": 1,
      "frame": 48,
      "pathData": "AqshBQIygRIJiHQI1AXopEFQnTBbmfA7g",
      "transform": {
        "x": 222.6,
        "y": 255
      },
      "color": "#000000"
    },
    {
      "strokeNumber": 2,
      "segment": 2,
      "frame": 51,
      "pathData": "AHqCtIAPicQADiejVAjQsfCvqWBgIjVkaQQNggOEmwQDOgwF2CvQF1CujJD3QhcBwhQC1QkzFMiiAAQi1AAACmjg",
      "transform": {
        "x": 292.2,
        "y": 260.2
      },
      "color": "#000000"
    },
    {
      "strokeNumber": 2,
      "segment": 3,
      "frame": 54,
      "pathData": "AGDNCIB2zYQADigjVAkQsfCwqWBfIjVkbQQNggOEmwQDOgvF2CuQF1CujJD4QjKD3iOI5IiDIPQiuCDhtAAQiAAAgli3g",
      "transform": {
        "x": 292.2,
        "y": 302.7
      },
      "color": "#000000"
    },
    {
      "strokeNumber": 3,
      "segment": 1,
      "frame": 72,
      "pathData": "AnwDDIgFj2QF/hHFshMQILBaoiELQlOAojwAAQhNAAhEgEg",
      "transform": {
        "x": 240,
        "y": 409.5
      },
      "color": "#000000"
    },
    {
      "strokeNumber": 3,
      "segment": 2,
      "frame": 75,
      "pathData": "AvcEOIgFj3QKgh8JmiOQGnhtD/EkQBWBzjkAVQi2AGkdA3Qr6CJm7AAQhNAAhEgEg",
      "transform": {
        "x": 289.2,
        "y": 402.1
      },
      "color": "#000000"
    },
    {
      "strokeNumber": 4,
      "segment": 1,
      "frame": 96,
      "pathData": "AjjE1QgBh8gHhsQgOjtg5hsQiEj+ALg1IEChPQKgCohTDIQguBYglD3IgGCEQjWHaiQAAQh9AAhLlag",
      "transform": {
        "x": 291.2,
        "y": 477.5
      },
      "color": "#000000"
    },
    {
      "strokeNumber": 4,
      "segment": 2,
      "frame": 99,
      "pathData": "AjMPcIgX09QgBh7gHhtQgOjtg5htQiEj9ALg1IEChPQKgCnhTDJQguBXglD5IhDXAQi4HJh7AAQhpAAg+lJg",
      "transform": {
        "x": 291.2,
        "y": 543.7
      },
      "color": "#000000"
    },
    {
      "strokeNumber": 4,
      "segment": 3,
      "frame": 102,
      "pathData": "Ai7YtMgAoglFQgBh7gHhtQgOjtg5htQiEj9ALg1IEChPQKgCnhTDJQguBXglD5MgB1An2QiFEBhsAAQhbAAhLivg",
      "transform": {
        "x": 291.2,
        "y": 587.6
      },
      "color": "#000000"
    },
    {
      "strokeNumber": 5,
      "segment": 1,
      "frame": 120,
      "pathData": "AlzDCIAtk1QC9gID+hGQIfBDpkEzQi+ANjaAAIgLAAg",
      "transform": {
        "x": 349.1,
        "y": 554.8
      },
      "color": "#000000"
    },
    {
      "strokeNumber": 5,
      "segment": 2,
      "frame": 123,
      "pathData": "AqEDxIAtk1QDogKFNhnQFMhoD/BOQCVAwhbCKQhZB/jtAyQl2BVohAAIgKAAg",
      "transform": {
        "x": 376.4,
        "y": 550.1
      },
      "color": "#000000"
    },
    {
      "strokeNumber": 6,
      "segment": 1,
      "frame": 144,
      "pathData": "AjNDpQgmkOg8i/QgSg2gHgsQg2jaDSAkQB+AYCQAtQD5BMgHB1QgLC3gJDGQipF7iMAAQh2AAhikZg",
      "transform": {
        "x": 163.2,
        "y": 588.6
      },
      "color": "#000000"
    },
    {
      "strokeNumber": 6,
      "segment": 2,
      "frame": 147,
      "pathData": "AiTJEIgFhiQgdrJh6mDQgSg2gHgsQg2jaDSAkQB+AYCQAtQD5BMgHB1QggIOgJKMQiLFqhzAAQhrAAhVlEg",
      "transform": {
        "x": 163.2,
        "y": 627.6
      },
      "color": "#000000"
    },
    {
      "strokeNumber": 6,
      "segment": 3,
      "frame": 150,
      "pathData": "AhRRxQgqlwgdrJQgdrIh6mDQgSg2gHgsQg2jbDSAlQB+AYCQAtQD5BLgHB2Qg3ODAOT0QhrDghiAAQhbAAhUjBg",
      "transform": {
        "x": 163.2,
        "y": 670.1
      },
      "color": "#000000"
    },
    {
      "strokeNumber": 7,
      "segment": 1,
      "frame": 168,
      "pathData": "AjRFCQj3iSj3koQj2kpF0A2QHZBKI4hlQKHAvpQH0QiUBKiFBLQhpBVh2AAQhqAAh2hFg",
      "transform": {
        "x": 135,
        "y": 798.9
      },
      "color": "#000000"
    },
    {
      "strokeNumber": 7,
      "segment": 2,
      "frame": 171,
      "pathData": "AtmH+Qj4iRj2kqQj3koF0A2QJwBiMVjOQIWiMHSiaQI/gVo3GQIkXBnQsVEeoZEwQhoBUh3AAQhqAAh2hFg",
      "transform": {
        "x": 201.2,
        "y": 780.1
      },
      "color": "#000000"
    },
    {
      "strokeNumber": 7,
      "segment": 3,
      "frame": 174,
      "pathData": "A0gKPQj3iRj3kqQj2koF0A2QJwBhMVjNQMVjPKBjuQKAjvBeCnQA4BllfCeQlgCesVEfQsUEfoZEwQhpBUh2AAQhrAAh2hFg",
      "transform": {
        "x": 245.3,
        "y": 765.6
      },
      "color": "#000000"
    },
    {
      "strokeNumber": 8,
      "segment": 1,
      "frame": 192,
      "pathData": "An4DUQnCizFjhGQIyhbIPhjQImAdpJETQkGAxkdA+QigAnh3AAQhKAAg7gPg",
      "transform": {
        "x": 621.6,
        "y": 197
      },
      "color": "#000000"
    },
    {
      "strokeNumber": 8,
      "segment": 2,
      "frame": 195,
      "pathData": "A0QF2QnCizFjhGQWXjnS6kbQKwDuuBDUQsCAnyDD6QigAoh3AAQhKAAg7gQg",
      "transform": {
        "x": 700.8,
        "y": 180.8
      },
      "color": "#000000"
    },
    {
      "strokeNumber": 8,
      "segment": 3,
      "frame": 198,
      "pathData": "AN+DSIAhilQAlivi7gIQsDAnyCD5QkFBBiYgpQnCixFjhHQWYjoS5kbQEpg0HOGFQCLCDiLCUQhWCBhYCVQk+EjioAAQjCAAAEmCg",
      "transform": {
        "x": 727.3,
        "y": 200.8
      },
      "color": "#000000"
    },
    {
      "strokeNumber": 8,
      "segment": 4,
      "frame": 201,
      "pathData": "ALBMDIDexgQAlivi7gJQsDAnyCD7QkFBAiYgoQnCizFjhHQWYjoS5kaQEpg1HOGGQCLCCiLCVQlAHflYLyQieB9hbAAQh5AAgFjcg",
      "transform": {
        "x": 727.3,
        "y": 240.2
      },
      "color": "#000000"
    },
    {
      "strokeNumber": 9,
      "segment": 1,
      "frame": 216,
      "pathData": "AkzCFQlpiuEZg6QEngZEkghQJMBRoNDPIiOAOQiFANhgAAQiHAAhAgZg",
      "transform": {
        "x": 602.4,
        "y": 349.5
      },
      "color": "#000000"
    },
    {
      "strokeNumber": 9,
      "segment": 2,
      "frame": 219,
      "pathData": "AuCDbQlpivEZg5QNyhJNjieQKIB5ptDvQpaAxqaBCQiFAOhhAAQiGAAhAgag",
      "transform": {
        "x": 661.5,
        "y": 340.9
      },
      "color": "#000000"
    },
    {
      "strokeNumber": 9,
      "segment": 3,
      "frame": 222,
      "pathData": "A03ELQlqivEag7QQAhTPsjHQKIiTEEFtQBPBzkDAJQv3A/zRB7QiFANhhAAQiGAAhAgZg",
      "transform": {
        "x": 705.2,
        "y": 336.2
      },
      "color": "#000000"
    },
    {
      "strokeNumber": 10,
      "segment": 1,
      "frame": 240,
      "pathData": "AjnIcQASkXAIkYQAenviykgQhwi1GlAeQHzAOhcEmIhOOgIgQC8Qj3Hnh9AAQh1AAgLmig",
      "transform": {
        "x": 545.3,
        "y": 280.4
      },
      "color": "#000000"
    },
    {
      "strokeNumber": 10,
      "segment": 2,
      "frame": 243,
      "pathData": "Al+SvQCqvxAcwKQAfnwiykfQhwi2GkAeQH0AOhdEmIhOOhQhYRfiyN9QjcE6huAAQiVAAA5pJg",
      "transform": {
        "x": 543.1,
        "y": 363
      },
      "color": "#000000"
    },
    {
      "strokeNumber": 10,
      "segment": 3,
      "frame": 246,
      "pathData": "EgJqAjgQJb+PA3/zQAenvixkgQhvi2GjAfQH0AOhcEmIhOOhQhuVrj3QOQiOLrjWJyQjXDrhuAAQiJAAAalug",
      "transform": {
        "x": 520.7,
        "y": 448.3
      },
      "color": "#000000"
    },
    {
      "strokeNumber": 10,
      "segment": 4,
      "frame": 249,
      "pathData": "EgS+A44QKsuCG705UAKTgfnAA8ghaQAenviykgQhwi2GlAfQH0AOhcEmIhOOhQhuVrj3QPUgGfAiCgQMAR2QmGGThnAAQgmAAACg4g",
      "transform": {
        "x": 461.5,
        "y": 554.1
      },
      "color": "#000000"
    },
    {
      "strokeNumber": 11,
      "segment": 1,
      "frame": 264,
      "pathData": "AuHBTIB5izQKghHLOhgQJxAmq2EjQmxBIl1BlQhjAZhcAAQj2AAjHi1g",
      "transform": {
        "x": 624.5,
        "y": 506.3
      },
      "color": "#000000"
    },
    {
      "strokeNumber": 11,
      "segment": 2,
      "frame": 267,
      "pathData": "A8ZDiIB5i0QVaiPYcj6QCXgaB7ghQKbErsRCZQ31A0waEcQhjAZhcAAQj2AAjHi1g",
      "transform": {
        "x": 715.9,
        "y": 492
      },
      "color": "#000000"
    },
    {
      "strokeNumber": 11,
      "segment": 3,
      "frame": 270,
      "pathData": "AVEHYQABkjgIk0QgIlMlMgIQ30A0waEcQlqBdkTj5IB6i0QVaiRYcj5QEWgwC6hLQBWgcBbAuQF5DKEcD4QB+B8h+DxQhuDwgzFqQjyIhihAAQidAAhPoMg",
      "transform": {
        "x": 755.1,
        "y": 543.4
      },
      "color": "#000000"
    },
    {
      "strokeNumber": 11,
      "segment": 4,
      "frame": 273,
      "pathData": "AT6SAQBgt2gdxvQgIlMlMgIQ30A0waEcQlqBdkTj5IB6i0QVaiRYcj5QEWgwC6hLQBWgcBbAuQF5DKEcD4QB+B8h+DxQifFdgjJVQgTJrgnIUQkHIWibAAQiiAAgqpKg",
      "transform": {
        "x": 755.1,
        "y": 617.6
      },
      "color": "#000000"
    },
    {
      "strokeNumber": 11,
      "segment": 5,
      "frame": 276,
      "pathData": "EAJMAnCQknojlGmHQjGjLB5AYQHrDKEeAoQDMAkBmiBQDikgBLv6QBgt0gdxwQgIlMlMgJQ30A1waEbQlqBekTj6IB6i0QVaiQYcj5QEWgwC6hLQBWgdBbAvQF5DKEcD4QB+B8h+DwQifFegjJWQgkS1h0NtQiORnqgEqQhVAfhFAAQiiAAhUing",
      "transform": {
        "x": 755.1,
        "y": 710.4
      },
      "color": "#000000"
    },
    {
      "strokeNumber": 12,
      "segment": 1,
      "frame": 288,
      "pathData": "AgkEEQg8nFjWjcQhUhcEbAXQFTAfAsC8QAfBnAbFHQh9FAhhAAQhTAAg9jjg",
      "transform": {
        "x": 565.1,
        "y": 661.5
      },
      "color": "#000000"
    },
    {
      "strokeNumber": 12,
      "segment": 2,
      "frame": 291,
      "pathData": "ABTLpQhLkug7oxQgyoDjpjvQhThbEaAXQFTAeAsC9QA7DAAtPhQAQGjhiA0QgUALgSAAQhSAAhDjJg",
      "transform": {
        "x": 567.5,
        "y": 707.4
      },
      "color": "#000000"
    },
    {
      "strokeNumber": 13,
      "segment": 1,
      "frame": 312,
      "pathData": "AoXg1QHlgXGBhmQGiAPnCD/IrlBXg",
      "transform": {
        "x": 628,
        "y": 625.4
      },
      "color": "#000000"
    },
    {
      "strokeNumber": 13,
      "segment": 2,
      "frame": 315,
      "pathData": "AFKCfIABhTQgEiKjFAXIyECHIhhjoQNqgqIlkqQEPhbHTE9QCtCPitCzQgkApgmA/QksFBieAAQijAAgNlSg",
      "transform": {
        "x": 686.8,
        "y": 633.7
      },
      "color": "#000000"
    },
    {
      "strokeNumber": 13,
      "segment": 3,
      "frame": 318,
      "pathData": "ADPK5QB7pTABmbQgEiLjFAYIyECIIhhjpQNqgqIlkqQEPhbHTE8QCtCPitC1QjFDcjiNfQiUBwhhAAQh9AAgmi6g",
      "transform": {
        "x": 686.8,
        "y": 672.3
      },
      "color": "#000000"
    },
    {
      "strokeNumber": 14,
      "segment": 1,
      "frame": 336,
      "pathData": "Amch1QD6gHFFgwQISAvpPEIIoCAig",
      "transform": {
        "x": 636.1,
        "y": 757.8
      },
      "color": "#000000"
    },
    {
      "strokeNumber": 14,
      "segment": 2,
      "frame": 339,
      "pathData": "As8hGQGggLJqh9QFwhJD5FOQAgBCiUgDI3/Bmg",
      "transform": {
        "x": 677.7,
        "y": 753.1
      },
      "color": "#000000"
    }
  ],
  "inLexicalListsHK": false,
  "stage1Words": [],
  "stage2Words": [],
  "fourCharacterPhrases": [],
  "classicalPhrases": [],
  "multiCharacterIdioms": [],
  "properNouns": [],
  "transliteratedWords": []
}