{
  "id": "4300",
  "character": "鎳",
  "sourceUrl": "https://www.edbchinese.hk/lexlist_ch/result.jsp?id=4300&sortBy=ks&jpC=lshk",
  "radical": "金",
  "strokeCount": 18,
  "jyutping": "",
  "pinyin": "",
  "strokeOrderImages": [
    "https://www.edbchinese.hk/EmbziciwebRes/stkdemo_js/4001-ZC/4300.html?lang=ch"
  ],
  "strokeVectors": [
    {
      "strokeNumber": 1,
      "segment": 1,
      "frame": 24,
      "pathData": "AmtE7IAIgYQCdnkgultQAmjMDMAfQDQBBESFLQA9CTi0EoIhHCoQlCHMijAAQidAAgLmlg",
      "transform": {
        "x": 330.5,
        "y": 220.1
      },
      "color": "#000000"
    },
    {
      "strokeNumber": 1,
      "segment": 2,
      "frame": 27,
      "pathData": "AqQNEIA8hnQE4ocCSm4IAIgYQCcnmgtlsQAljMDMAfQDQBBETFLQA9CTi0EpIhHCoIgHAPQjmIUkIHYIgpBMQnJHqicAAQiWAACGnPg",
      "transform": {
        "x": 301.4,
        "y": 276.4
      },
      "color": "#000000"
    },
    {
      "strokeNumber": 1,
      "segment": 3,
      "frame": 30,
      "pathData": "AuuU9QFVnwEvorIA8hnQE3obCSm5IAIgYQCdnmgulsQAmjMDMAfQDQBBETFLQA9CTi0EpIhHCoIgHAPQjmIVkIHXIgqBMQjCFVjUE0QipD5i1DjQnPHJiGAAQiMAADdn4g",
      "transform": {
        "x": 265.6,
        "y": 331
      },
      "color": "#000000"
    },
    {
      "strokeNumber": 1,
      "segment": 4,
      "frame": 33,
      "pathData": "EgXtAiGIDLi3QHRoAGYpTQFWnwEtoqIA8hnQE4ocCSm5IAIgYQCdnlgultQAmjMDMAfQDQBBETFLQA9CTi0EpIhHCoIgGAPQjmIVkIHYIgrBMQjCFUjVE0QipD5i1DjQp0MVsLITQiEAjg9AAQhtAAB2hwg",
      "transform": {
        "x": 215.5,
        "y": 375.9
      },
      "color": "#000000"
    },
    {
      "strokeNumber": 2,
      "segment": 1,
      "frame": 48,
      "pathData": "Ag5EJQmYmUhBjoQJaCXFUCxQD/GfkiAAQiTABkfhsg",
      "transform": {
        "x": 393.2,
        "y": 260.3
      },
      "color": "#000000"
    },
    {
      "strokeNumber": 2,
      "segment": 2,
      "frame": 51,
      "pathData": "AjUAiQmYmUhBjpQJbCYFTCxQDVBvBuB5QDUFUjUEVQgqAdg1AAQjrAAnOo6g",
      "transform": {
        "x": 408.7,
        "y": 283.5
      },
      "color": "#000000"
    },
    {
      "strokeNumber": 3,
      "segment": 1,
      "frame": 72,
      "pathData": "ArFhMQHLgrGGhTQNwAanfE4QlgA5lvAKQn8gBgXkWg",
      "transform": {
        "x": 284.6,
        "y": 459.8
      },
      "color": "#000000"
    },
    {
      "strokeNumber": 3,
      "segment": 2,
      "frame": 75,
      "pathData": "AyOA9QHLgrGHhRQHBhfFpiTQEoh3FMEbQCACTjqAaQnECkngBOQlfA5lwAKQn8gBgXkXg",
      "transform": {
        "x": 330.3,
        "y": 446
      },
      "color": "#000000"
    },
    {
      "strokeNumber": 4,
      "segment": 1,
      "frame": 96,
      "pathData": "AqXC0QmcitEohEQIig6Ijh1QOxApo5EAImOBHQlPBpkKAAQjEAAieg5g",
      "transform": {
        "x": 257.7,
        "y": 578
      },
      "color": "#000000"
    },
    {
      "strokeNumber": 4,
      "segment": 2,
      "frame": 99,
      "pathData": "AzRE2QmciuEphEQIig6Ikh0QHuhqHxiZQKQAYBOCfQAdCKnZBKI0XDoQlQBokKAAQjEAAifg4g",
      "transform": {
        "x": 314.7,
        "y": 565
      },
      "color": "#000000"
    },
    {
      "strokeNumber": 5,
      "segment": 1,
      "frame": 120,
      "pathData": "AjhgaQgqlXjljQQKdhtFCE4QANCohDB+IgKASQinKcimAAQihAAiip4g",
      "transform": {
        "x": 310.5,
        "y": 525.3
      },
      "color": "#000000"
    },
    {
      "strokeNumber": 5,
      "segment": 2,
      "frame": 123,
      "pathData": "AiuMWIgz0mQgqlXjljQQKdhsFCE3QANCphDB+IgKARQhALbgEJgQh4FNiIAAQiEAAiVk+g",
      "transform": {
        "x": 310.5,
        "y": 575.5
      },
      "color": "#000000"
    },
    {
      "strokeNumber": 5,
      "segment": 3,
      "frame": 126,
      "pathData": "Ah7YDMgBmgpMQgqlXjljQQKdhsFCE3QANCohDB+IgKASQhALcgEJfQgVLkgnGQQiLFLiAAAQhSAAhNiKg",
      "transform": {
        "x": 310.5,
        "y": 632.4
      },
      "color": "#000000"
    },
    {
      "strokeNumber": 6,
      "segment": 1,
      "frame": 144,
      "pathData": "AjWAbQjFjZAgg1QFFgoG1DzQAQEiirAAQiWAAkkjfg",
      "transform": {
        "x": 198.4,
        "y": 682.2
      },
      "color": "#000000"
    },
    {
      "strokeNumber": 6,
      "segment": 2,
      "frame": 147,
      "pathData": "AA8FdQiniJi+mTQjFjaAhg1QFEgoG2DzQDiDkhRFfQhICUhnAAQhdAAh2h3g",
      "transform": {
        "x": 206.6,
        "y": 704.1
      },
      "color": "#000000"
    },
    {
      "strokeNumber": 7,
      "segment": 1,
      "frame": 168,
      "pathData": "AlEApQA4i1AmjRQBOigGBFYQDzEFjzB8IgnAcIgBABQhNAihSAxQiWBFhcAAQjSAABelog",
      "transform": {
        "x": 430.8,
        "y": 646.4
      },
      "color": "#000000"
    },
    {
      "strokeNumber": 7,
      "segment": 2,
      "frame": 171,
      "pathData": "AnqIEQC9kBBylsQA4i2AmjRQBOifGBFXQDyEGjyB7IgnAdIgBAAQhNAihSAxQilBii6CeQi7BqhKAAQgpAAgIgfg",
      "transform": {
        "x": 417.1,
        "y": 661.1
      },
      "color": "#000000"
    },
    {
      "strokeNumber": 8,
      "segment": 1,
      "frame": 192,
      "pathData": "Apsh2QiwkwFUA+QEvAlFDglQNrgopvI7IkOC3QggASgpAAQjZAAninqg",
      "transform": {
        "x": 149.1,
        "y": 847.5
      },
      "color": "#000000"
    },
    {
      "strokeNumber": 8,
      "segment": 2,
      "frame": 195,
      "pathData": "Aw4gDQivkwFTA+QEwAmFEglQG8gzHji/QLsBXlwDtQoyDfntDhIkPC4QgfARgpAAQjaAAnjnqg",
      "transform": {
        "x": 195,
        "y": 836
      },
      "color": "#000000"
    },
    {
      "strokeNumber": 8,
      "segment": 3,
      "frame": 198,
      "pathData": "A3xCCQiwkwFUA/QEvAlFEglQG9gyHii/IM3jwQM1hvl5FTQnPComoCoQoyDentDiIkOC3QggARgpAAQjaAAninqg",
      "transform": {
        "x": 239.2,
        "y": 822.6
      },
      "color": "#000000"
    },
    {
      "strokeNumber": 8,
      "segment": 4,
      "frame": 201,
      "pathData": "A9qERQiwkvFUA9QEvAmFEglQG9gyHji/Ib7oJQGFhogqDlQgcCGmXBiQjdBMjUBNQnPCnmoCnQoxDgnuDhIkOC4QggARgpAAQjaAAninrg",
      "transform": {
        "x": 276.9,
        "y": 808.3
      },
      "color": "#000000"
    },
    {
      "strokeNumber": 9,
      "segment": 1,
      "frame": 216,
      "pathData": "An6D7QBnl0AAkwQB4iPJSEzQFUDyjwBpIiDCfQmmDijFAAQjCAAAbjcg",
      "transform": {
        "x": 678.9,
        "y": 137.3
      },
      "color": "#000000"
    },
    {
      "strokeNumber": 9,
      "segment": 2,
      "frame": 219,
      "pathData": "ApaIGQB6klBIkBQBol1AAkxQB4iOJSEyQFUDyjwBqIiDCfQkTFKjjD5QkIDYh5AAQh+AAAgjug",
      "transform": {
        "x": 669,
        "y": 165.7
      },
      "color": "#000000"
    },
    {
      "strokeNumber": 9,
      "segment": 3,
      "frame": 222,
      "pathData": "ArNNWQCLkQBoj4QB6kkBIkCQBol1AAkxQB3iOJSEyQFVDyjxBqIiDCfQkSFKjlD5QjSDnisCgQkGDBhGAAQguAAAohWg",
      "transform": {
        "x": 656.3,
        "y": 184.1
      },
      "color": "#000000"
    },
    {
      "strokeNumber": 10,
      "segment": 1,
      "frame": 240,
      "pathData": "AiqBJQgpjag2i2QhokLIGDHQB4BTAPF8QhNGdhyAAQhwAAiXmYg",
      "transform": {
        "x": 553.1,
        "y": 300.4
      },
      "color": "#000000"
    },
    {
      "strokeNumber": 10,
      "segment": 2,
      "frame": 243,
      "pathData": "AhPIxQghoXhNmXQgqjbg2i2QhokLIGDHQB5BTAOF9IAnPjQhcFHhdAAQhjAAhil3g",
      "transform": {
        "x": 555.1,
        "y": 345.9
      },
      "color": "#000000"
    },
    {
      "strokeNumber": 10,
      "segment": 3,
      "frame": 246,
      "pathData": "AhCO6IAAAAIAAgbIAAgCQgEl5gVlIQghoWhNmXQgqjbg2i2QhokMIGDIQB5BSAOF9IA/ZJQg9GLhmAAQhdAAh9lDg",
      "transform": {
        "x": 556.3,
        "y": 379.9
      },
      "color": "#000000"
    },
    {
      "strokeNumber": 10,
      "segment": 4,
      "frame": 249,
      "pathData": "AhgUbIASjAIAAoAIAAgbIAAgCQgEl4gVlIQghoWhNmYQgqjbg2i2QhokMIGDIQB5BSAOF9MABXAiuQgjHYiUALIgPABQiXAAhKlBg",
      "transform": {
        "x": 557.5,
        "y": 415
      },
      "color": "#000000"
    },
    {
      "strokeNumber": 11,
      "segment": 1,
      "frame": 264,
      "pathData": "AtGggQGngxIghlQPwhqmmD6QlZBCm9B6QkLBBitAAQlVAAASj3g",
      "transform": {
        "x": 639.3,
        "y": 270.9
      },
      "color": "#000000"
    },
    {
      "strokeNumber": 11,
      "segment": 2,
      "frame": 267,
      "pathData": "AN+A3QgniNhmAkQklg1pUByQlZBDm+B6QsWC/Abl2QGngwIhhlQLViGOvjkQH+B+DqEqQAJBGhECTQjgFciwAAQjGAAiLm4g",
      "transform": {
        "x": 724.5,
        "y": 265.9
      },
      "color": "#000000"
    },
    {
      "strokeNumber": 11,
      "segment": 3,
      "frame": 270,
      "pathData": "APSHCQgMmagxnMQgBiNgWhSQgniOhmAkQklg1pUBzQlZBDm+B6QsWC/Abl2QGngxIhhlQLViGOvjkQH+B+DqEqQAJBHhECTQgkBOg7BlQhAD+AjJnIAYHKQhyDvhoAAQi3AAiYrog",
      "transform": {
        "x": 724.5,
        "y": 335.8
      },
      "color": "#000000"
    },
    {
      "strokeNumber": 11,
      "segment": 4,
      "frame": 273,
      "pathData": "AQ6aqQi4kqATlBQBRodgUqrQgMmagxnNQgBiNgWhRQgniOhmAkQklg1pUBzQlZBCm+B7QsWC+Abl2QGngwIhhlQLViHOvjkQH+B+DqErQAJBGhECTQgkBPg7BkQhAD+AjJoIAwOVQAvGyi2EiQhfDnhvAAQg/AAhFhMg",
      "transform": {
        "x": 724.5,
        "y": 394.5
      },
      "color": "#000000"
    },
    {
      "strokeNumber": 12,
      "segment": 1,
      "frame": 288,
      "pathData": "AsehqQGUAGHBhAQSfhCq6EoIrQBYQiJAXhqAAQl0AAgDkbg",
      "transform": {
        "x": 646,
        "y": 360.4
      },
      "color": "#000000"
    },
    {
      "strokeNumber": 12,
      "segment": 2,
      "frame": 291,
      "pathData": "A1iAbQGUAGHCg/QI9hSKJjGQLlBAhBERMghWAEFQiJAXhqAAQl0AAgDkcg",
      "transform": {
        "x": 704,
        "y": 347
      },
      "color": "#000000"
    },
    {
      "strokeNumber": 13,
      "segment": 1,
      "frame": 312,
      "pathData": "Ar7hHQGugZHkhSQPQgMo9EjQkLAfkfAcQiuAUiHAAQnnAAAhj7g",
      "transform": {
        "x": 645.4,
        "y": 446.7
      },
      "color": "#000000"
    },
    {
      "strokeNumber": 13,
      "segment": 2,
      "frame": 315,
      "pathData": "A1CAyQGugZHmhSQIChXJDiZQKpgkAFFiQpaBwsHBaQkLAfkfAcQivATiHAAQnnAAAhj7g",
      "transform": {
        "x": 703.6,
        "y": 434.5
      },
      "color": "#000000"
    },
    {
      "strokeNumber": 14,
      "segment": 1,
      "frame": 336,
      "pathData": "ArBiLQGWAVIqhKQLNBOmTDiIrdBDQhpAOhUAAQmdAAA9lMg",
      "transform": {
        "x": 637.7,
        "y": 530.8
      },
      "color": "#000000"
    },
    {
      "strokeNumber": 14,
      "segment": 2,
      "frame": 339,
      "pathData": "A0/g7QGWAVIshLQGRg2HhhpIFmAUQH+BUgSEjIquAAI27CIQhoAOhVAAQmdAAA9lMg",
      "transform": {
        "x": 701.4,
        "y": 522.8
      },
      "color": "#000000"
    },
    {
      "strokeNumber": 15,
      "segment": 1,
      "frame": 360,
      "pathData": "AnXB0Qn6jGESiLINugXQNagRk/FHQjzArj4A4QiJBQiXAAQi/AAjXiBg",
      "transform": {
        "x": 554.4,
        "y": 682
      },
      "color": "#000000"
    },
    {
      "strokeNumber": 15,
      "segment": 2,
      "frame": 363,
      "pathData": "AxfDIQn5jHERiKINvgXQEzhAQXhoQPmCKr7DQQoCAloYBfQjzArj4A4QiJBQiXAAQjAAAjXiBg",
      "transform": {
        "x": 619.1,
        "y": 673.6
      },
      "color": "#000000"
    },
    {
      "strokeNumber": 15,
      "segment": 3,
      "frame": 366,
      "pathData": "A7ZEZQn5jIERiKINvgWQEzhAQXhpQF0glHSgqII1hSQMxCFreFiInaAAQl+gHmLAcQoBAkoYBfQj0Asj4A3QiJBRiXAAQjAAAjXiBg",
      "transform": {
        "x": 682.5,
        "y": 665.5
      },
      "color": "#000000"
    },
    {
      "strokeNumber": 15,
      "segment": 4,
      "frame": 369,
      "pathData": "EgiGAFCQn5jIERiKINvgWQEzhAQYhpQFzglHSgqIRrikQElBLEeCwQFGDzmdBLI2pAAQl+gHmLAcQoBAkoYBgQj0Arj4A3QiJBRiXAAQjAAAjXiBg",
      "transform": {
        "x": 725.4,
        "y": 661.4
      },
      "color": "#000000"
    },
    {
      "strokeNumber": 16,
      "segment": 1,
      "frame": 384,
      "pathData": "AkMBvQggmIhQkWQAFmKKxFkQBzB4hSDaQgWCcgSCdQiCLJiTAAQiNAAidqQg",
      "transform": {
        "x": 703.7,
        "y": 632.7
      },
      "color": "#000000"
    },
    {
      "strokeNumber": 16,
      "segment": 2,
      "frame": 387,
      "pathData": "Aj/LUQAXpLgkm5QggmJhQkWQAFmKKxFjQBzB4hSDaQgWCcgSCeQg9IXgKIxQiLHBh5AAQh8AAhrnLg",
      "transform": {
        "x": 703.7,
        "y": 674.3
      },
      "color": "#000000"
    },
    {
      "strokeNumber": 16,
      "segment": 3,
      "frame": 390,
      "pathData": "Aj/TyIAAxXQAXpKgkm6QggmJhQkWQAFmKKxFjQBzB4hSDaQgWCcgSCeQg9IYgKIwQgKJzA2KSQiUEuh5AAQiaAAhwnmg",
      "transform": {
        "x": 703.7,
        "y": 731.2
      },
      "color": "#000000"
    },
    {
      "strokeNumber": 16,
      "segment": 4,
      "frame": 393,
      "pathData": "EgANAi9QlqmHAemHIARgbQA2hZATlcIAA0qQAXpLgkm6QggmJhQkWQAFmKKxFjQBzB4hSDaQgWCcgSCeQg9IYgKIxQgKJyA2KSQANCZAQCbIgFGDQhmJFjCAAQgKAAgLgCg",
      "transform": {
        "x": 703.7,
        "y": 779.9
      },
      "color": "#000000"
    },
    {
      "strokeNumber": 17,
      "segment": 1,
      "frame": 408,
      "pathData": "AnKENQHEn5BPlRQD6AcCIFwQh6DaipDZQlDE8icAAQiaAAAHkxg",
      "transform": {
        "x": 652.5,
        "y": 721.1
      },
      "color": "#000000"
    },
    {
      "strokeNumber": 17,
      "segment": 2,
      "frame": 411,
      "pathData": "AqwIRQFolJD3kVQHDn6BQlQQD6AbCIFwQh5DbiqDZQk3GOnZGIQl9DaiKAAQi4AAD+mHg",
      "transform": {
        "x": 614.8,
        "y": 755.7
      },
      "color": "#000000"
    },
    {
      "strokeNumber": 17,
      "segment": 3,
      "frame": 414,
      "pathData": "A22UFIFljyQJendG3mSQFmlHD4kWQHDn6BQlRQD6AcCIFwQh5DbipDZQk4GPnaGHQlOEVmeERQsRGNkvAAIgNAAg",
      "transform": {
        "x": 552.1,
        "y": 792.2
      },
      "color": "#000000"
    },
    {
      "strokeNumber": 18,
      "segment": 1,
      "frame": 432,
      "pathData": "AhADZQj0jWjeiTIAAj/QIbC9HTETQCHFPjHAAQiTAAlJi3g",
      "transform": {
        "x": 773.1,
        "y": 734.5
      },
      "color": "#000000"
    },
    {
      "strokeNumber": 18,
      "segment": 2,
      "frame": 435,
      "pathData": "ABTGSQj0j/jijFQj0jWjeiUIAAj/QIcC9HSEUQDpCLDYCfQGcI8kGAAQiyAAnrkKg",
      "transform": {
        "x": 805.4,
        "y": 761.3
      },
      "color": "#000000"
    },
    {
      "strokeNumber": 18,
      "segment": 3,
      "frame": 438,
      "pathData": "AEzKCQiFiJiGiUQhuh6hshwQj1j+jjjHQjzjVjeiUIAAj/QIbC9HTEUQDpCKDXCgIH3F4QCVBgB1CGQAyIMkIAAQjKAAmBkxg",
      "transform": {
        "x": 831.6,
        "y": 789.2
      },
      "color": "#000000"
    },
    {
      "strokeNumber": 18,
      "segment": 4,
      "frame": 441,
      "pathData": "APRSYQmblUmxnAQiEiKiGiTQhvh6hshvQj1j/jijHQj0jVjeiUIAAj/QIcC8HTEVQDpCKDXCgIH2F5QCVBfB1CFQD2EYBqHAQAdExjJAAQg7AAhOgZg",
      "transform": {
        "x": 849,
        "y": 814.6
      },
      "color": "#000000"
    }
  ],
  "inLexicalListsHK": false,
  "stage1Words": [],
  "stage2Words": [],
  "fourCharacterPhrases": [],
  "classicalPhrases": [],
  "multiCharacterIdioms": [],
  "properNouns": [],
  "transliteratedWords": []
}