{
  "id": "4306",
  "character": "鏈",
  "sourceUrl": "https://www.edbchinese.hk/lexlist_ch/result.jsp?id=4306&sortBy=ks&jpC=lshk",
  "radical": "金",
  "strokeCount": 19,
  "jyutping": "lin6",
  "pinyin": "liɑ̀n",
  "strokeOrderImages": [
    "https://www.edbchinese.hk/EmbziciwebRes/stkdemo_js/4001-ZC/4306.html?lang=ch"
  ],
  "strokeVectors": [
    {
      "strokeNumber": 1,
      "segment": 1,
      "frame": 24,
      "pathData": "Al9BeQCJoCgWmCQBHjRFmDRQFhDfhJD3IipHVIgUAqQnILhijAAQirAACbsyg",
      "transform": {
        "x": 294.8,
        "y": 250.8
      },
      "color": "#000000"
    },
    {
      "strokeNumber": 1,
      "segment": 2,
      "frame": 27,
      "pathData": "AqEOGQFbrfCYo+QCIoDgVmCQBGjRFnDRQFhDfhJD3IipHWIqUWMQk/FqiDgBQibAABvn/g",
      "transform": {
        "x": 271.2,
        "y": 301
      },
      "color": "#000000"
    },
    {
      "strokeNumber": 1,
      "segment": 3,
      "frame": 30,
      "pathData": "AupYGQBLh+BLiEQDwm2C5mIQFcreCXo/QCIoDgVmCQBGjRFoDRQFgDfhID3IiqHWIqUWMQjMGvkUGUQmeGniMAAQh5AABWlAg",
      "transform": {
        "x": 242.9,
        "y": 345.8
      },
      "color": "#000000"
    },
    {
      "strokeNumber": 1,
      "segment": 4,
      "frame": 33,
      "pathData": "EgWMAkGQHlobG9rnQBMh+BKiEQDxm2C4mHQFbrfCYo/QCIoDgVmCQBHjRFnDRQFhDfhJD3IipHWIqVWMQjMGvkUGUQmTJPosIWQmAFFh5AAQg2AAgBhBg",
      "transform": {
        "x": 198.2,
        "y": 397.2
      },
      "color": "#000000"
    },
    {
      "strokeNumber": 2,
      "segment": 1,
      "frame": 48,
      "pathData": "Ah3BVQipi/idhwIBHhQQHIAaFWDiQBKFZizAAQiNAAkpjWg",
      "transform": {
        "x": 347.7,
        "y": 275.9
      },
      "color": "#000000"
    },
    {
      "strokeNumber": 2,
      "segment": 2,
      "frame": 51,
      "pathData": "AgeCeQh8irh3iGQipjAidhwIBHhQQHJAaFVDiQB7BRBsBrQDFFojFDlQg1Aig5AAQi9AAjol2g",
      "transform": {
        "x": 363.1,
        "y": 299.3
      },
      "color": "#000000"
    },
    {
      "strokeNumber": 3,
      "segment": 1,
      "frame": 72,
      "pathData": "ArhCoIC+jlQENgCEqhEIAhgHQQhjZo9HqQmHBHlsAAQkLAAj8gmg",
      "transform": {
        "x": 259.9,
        "y": 470.3
      },
      "color": "#000000"
    },
    {
      "strokeNumber": 3,
      "segment": 2,
      "frame": 75,
      "pathData": "AwVDnIC+jmQEOgCErhDIAhgHQD5g8ENhnQGQhbFoC/QBqC6m1ArQjsBBjkApQmGBHluAAQkKAAj9glg",
      "transform": {
        "x": 290.6,
        "y": 464
      },
      "color": "#000000"
    },
    {
      "strokeNumber": 4,
      "segment": 1,
      "frame": 96,
      "pathData": "Am6DvQnLh9B3iaQJchHIfiJQNEgJrnFuQoWCMj6AAQhFAAgvgKg",
      "transform": {
        "x": 232.3,
        "y": 597.2
      },
      "color": "#000000"
    },
    {
      "strokeNumber": 4,
      "segment": 2,
      "frame": 99,
      "pathData": "Au5FqQnMh9B4ibQJbhGIhiJQGGhiFpiGQFjhAFjDWQAcB8kgAuIxVENQoXCNj5AAQhFAAgvgLg",
      "transform": {
        "x": 283.5,
        "y": 584.9
      },
      "color": "#000000"
    },
    {
      "strokeNumber": 5,
      "segment": 1,
      "frame": 120,
      "pathData": "AigBIQAdoBkWhGQM/iDgNEmIhPEaIAAAAQiCJqiDAAQhyAAhzngg",
      "transform": {
        "x": 284.2,
        "y": 535
      },
      "color": "#000000"
    },
    {
      "strokeNumber": 5,
      "segment": 2,
      "frame": 123,
      "pathData": "AiAKZQgRoKgPpWQAdoCkWhFQM/iEgNEnIhPEZIAAAAQgBJWgOIdQiJIXh1AAQhmAAhXmfg",
      "transform": {
        "x": 284.2,
        "y": 587.7
      },
      "color": "#000000"
    },
    {
      "strokeNumber": 5,
      "segment": 3,
      "frame": 126,
      "pathData": "AhGXSQggpegasFQgRoKgPpWQAdoCkWhGQM/iDgNEmIhPEaIAAAAQgBJXgOIcQgWM8g1KzQhCB8hKAAQhRAAhZiQg",
      "transform": {
        "x": 284.2,
        "y": 643.2
      },
      "color": "#000000"
    },
    {
      "strokeNumber": 6,
      "segment": 1,
      "frame": 144,
      "pathData": "Ah8BwIiqliQCRhuGeEYQBVFaiZAAQhpAAjYiig",
      "transform": {
        "x": 185.6,
        "y": 702.4
      },
      "color": "#000000"
    },
    {
      "strokeNumber": 6,
      "segment": 2,
      "frame": 147,
      "pathData": "Ag/EJIlUrGQCRhuGeEYQFMCuhwG+QhNCEhfAAQh4AAiTjUg",
      "transform": {
        "x": 196.5,
        "y": 722.7
      },
      "color": "#000000"
    },
    {
      "strokeNumber": 7,
      "segment": 1,
      "frame": 168,
      "pathData": "Ak6BuQBmkyAJilQCJgpFWFVQB3CLj5CgQi7CAhvAAQieAAgEkAg",
      "transform": {
        "x": 395.5,
        "y": 662.3
      },
      "color": "#000000"
    },
    {
      "strokeNumber": 7,
      "segment": 2,
      "frame": 171,
      "pathData": "AmxIbQCZlpBWkBQBmkzAJilQCIgpFXFVQB3CMj5CfQoqH8h1AAQgWAAgGgRg",
      "transform": {
        "x": 383.5,
        "y": 681.3
      },
      "color": "#000000"
    },
    {
      "strokeNumber": 8,
      "segment": 1,
      "frame": 192,
      "pathData": "AoMgWQlAl1FeAhQDaAgD6gTIAYgCIAWgCQPfhLn1IzQiOBJh7BFQhMBZhsAAQjgAAlpmEg",
      "transform": {
        "x": 160.6,
        "y": 845.5
      },
      "color": "#000000"
    },
    {
      "strokeNumber": 8,
      "segment": 2,
      "frame": 195,
      "pathData": "AuwBbQlAlzFeAgQDbAhD5gUIAZgCIAWgCQFdgiGWiHQRbjloyHzQnVDQldC0QiOBJh6BEQhMBahsAAQjhAAlqmGg",
      "transform": {
        "x": 202.5,
        "y": 834.1
      },
      "color": "#000000"
    },
    {
      "strokeNumber": 8,
      "segment": 3,
      "frame": 198,
      "pathData": "A0QDZQlAl0FeAhQDaAhD6gUIAYgCIAXgCQFcgiGWiHQI4iXGticQJihPjYEoQnKC+l8CpQnVDRlcC0QiOBJh7BEQhMBahsAAQjhAAlpmGg",
      "transform": {
        "x": 237.8,
        "y": 821.5
      },
      "color": "#000000"
    },
    {
      "strokeNumber": 8,
      "segment": 4,
      "frame": 201,
      "pathData": "A3QE2QlAlzFeAgQDaAgD6gTIAYgCIAXgCQFcgiGXiHQI3iXGticQDuhWDEhXQFWhWA6CmQAFCrm9CLQnKC+l8CpQnTDRleC0QiOBJh7BEQhMBahsAAQjgAAlqmGg",
      "transform": {
        "x": 257,
        "y": 812.2
      },
      "color": "#000000"
    },
    {
      "strokeNumber": 9,
      "segment": 1,
      "frame": 216,
      "pathData": "AmuCQQlPirCvhYQEygZEVgiQQpAJqSEzQkXAhjSAAQjKAAiLgfg",
      "transform": {
        "x": 659.2,
        "y": 296.6
      },
      "color": "#000000"
    },
    {
      "strokeNumber": 9,
      "segment": 2,
      "frame": 219,
      "pathData": "AvODiQlQisCwhXQExgZEWgiQH2g+GahcQTXg9pYFSIoNBfQlYBBkTAhQkXAgjTAAQjKAAiKgeg",
      "transform": {
        "x": 713.7,
        "y": 288.4
      },
      "color": "#000000"
    },
    {
      "strokeNumber": 9,
      "segment": 3,
      "frame": 222,
      "pathData": "A0sFvQlPisCvhYQEygYEVgjQH2g8GbhdQIOh2F6ipQDnghFTC3QDODfoEBgIwaC+QlXBBkUAhQkYAhjSAAQjKAAiLgfg",
      "transform": {
        "x": 748.6,
        "y": 274.3
      },
      "color": "#000000"
    },
    {
      "strokeNumber": 10,
      "segment": 1,
      "frame": 240,
      "pathData": "AhmBjQhWk/iOiOQgujiGgCHQDvBdA5IQQgxFQhmAAQhwAAivmVg",
      "transform": {
        "x": 605.2,
        "y": 433.4
      },
      "color": "#000000"
    },
    {
      "strokeNumber": 10,
      "segment": 2,
      "frame": 243,
      "pathData": "AgOJQQgWiYgXi+Qgikrg7jaQhWlAiOiOQgujiGhCHQDuBdA5IRQAJBdAFBpQBAEdAVEcQg+EvhngBQhjAAiHkXg",
      "transform": {
        "x": 610.2,
        "y": 470.1
      },
      "color": "#000000"
    },
    {
      "strokeNumber": 10,
      "segment": 3,
      "frame": 246,
      "pathData": "AB9O1QhGhVhKoBQgXiYgWi+Qgikrg7jaQhWlAiOiOQgujiGhCHQDuBdA5IRQAJBdAFBqQBAEcAVEcQAXE3gcE2QgdCkg+AAQg/AAhgikg",
      "transform": {
        "x": 610.7,
        "y": 494.2
      },
      "color": "#000000"
    },
    {
      "strokeNumber": 11,
      "segment": 1,
      "frame": 264,
      "pathData": "AujghQGNACGmg4QCrgXCxggQVJjMz8GmIoYBlQiwAgiFAAQlsAAgjjyg",
      "transform": {
        "x": 688.6,
        "y": 393.3
      },
      "color": "#000000"
    },
    {
      "strokeNumber": 11,
      "segment": 2,
      "frame": 267,
      "pathData": "A59CaQGOADGmg4QCsgXCxghQKrh9LqkRQEdh3F8DKQD3LzsOmYQhphQkTA7I5oE2QiwAgiEAAQltAAgjj0g",
      "transform": {
        "x": 761.6,
        "y": 374.5
      },
      "color": "#000000"
    },
    {
      "strokeNumber": 11,
      "segment": 3,
      "frame": 270,
      "pathData": "AN3GBQAxkwADjxQAYiahThAQhqhRkTA7I5nE2QqVB4gvlLQGNACGmg4QCtgXCwggQKrh/LqkRQEdh2F9DJQBjA1BpBKQE5DshxBfQiiCzi/KoQjFEJiHAAQi0AAhDnWg",
      "transform": {
        "x": 780.3,
        "y": 420.1
      },
      "color": "#000000"
    },
    {
      "strokeNumber": 11,
      "segment": 4,
      "frame": 273,
      "pathData": "ALFLaQB4m4A6liQAxkwADjxQAYiahThBQhqhRkTA8I5nE2QqVB4gvlMQGNADGmg4QCtgXCwghQKrh+LqkRQEdh3F9DKQBjA0BpBKQE5DthxBeQiiCzi/KpQgmCHgnCaQjvOPkPgpQgVAEgTAAQjnAABlo+g",
      "transform": {
        "x": 780.3,
        "y": 465.1
      },
      "color": "#000000"
    },
    {
      "strokeNumber": 12,
      "segment": 1,
      "frame": 288,
      "pathData": "AmoCFQmtjUF7gbQEDgODkgZQOTgnmJENQmrBCkXAAQiTAAhqgSg",
      "transform": {
        "x": 718.7,
        "y": 476.8
      },
      "color": "#000000"
    },
    {
      "strokeNumber": 12,
      "segment": 2,
      "frame": 291,
      "pathData": "ArqDYQmtjVF7gaQEDgODlgZQIMg5FvhyQDhgCCbCsQBVCaoXAZQieAdiPAXQmqBCkXAAQiTAAhqgSg",
      "transform": {
        "x": 750.9,
        "y": 468.5
      },
      "color": "#000000"
    },
    {
      "strokeNumber": 13,
      "segment": 1,
      "frame": 312,
      "pathData": "ApihnQEQgiE/g1QSbBeuHDxIlbAqQhNAEhCAAQobAACikmg",
      "transform": {
        "x": 694.3,
        "y": 571.5
      },
      "color": "#000000"
    },
    {
      "strokeNumber": 13,
      "segment": 2,
      "frame": 315,
      "pathData": "AvAgcQEQgiE+g2QFxg+GuhXQN5BPnzEpIzrCXQhNAEhCAAQobAACikmg",
      "transform": {
        "x": 729.3,
        "y": 564
      },
      "color": "#000000"
    },
    {
      "strokeNumber": 13,
      "segment": 3,
      "frame": 318,
      "pathData": "Ay7ADQERgiE+g1QFxg+GthYIEtg+QJNAGC1FNIqoBkIzsCWQhMAEhDAAQoaAAChkmg",
      "transform": {
        "x": 754.4,
        "y": 560.8
      },
      "color": "#000000"
    },
    {
      "strokeNumber": 14,
      "segment": 1,
      "frame": 336,
      "pathData": "ArsAeQkSjFEIgMQEQgCGpgrQaVgh0ZFUQjvArj3A2QhIAwhYAAQixAAj0jGg",
      "transform": {
        "x": 632,
        "y": 690.2
      },
      "color": "#000000"
    },
    {
      "strokeNumber": 14,
      "segment": 2,
      "frame": 339,
      "pathData": "A3LBxQkTjFEJgMQEQgCGpgrQGAgnH8hIII6g6QXdAmtSEKQsiAGujCmQjvArj4A2QhIAwhXAAQiyAAjzjGg",
      "transform": {
        "x": 705.6,
        "y": 681.9
      },
      "color": "#000000"
    },
    {
      "strokeNumber": 14,
      "segment": 3,
      "frame": 342,
      "pathData": "A/eC8QkSjFEIgMQEQgCGpgrQGBgmH9hJIZTikQFjhFCRAnQH9DNgsCbQgXA9g+AWQkTAcvtggQsgAGukCnQjvArj4A2QhIAwhYAAQixAAj0jGg",
      "transform": {
        "x": 758.6,
        "y": 674.4
      },
      "color": "#000000"
    },
    {
      "strokeNumber": 15,
      "segment": 1,
      "frame": 360,
      "pathData": "Ai+FXQgHrtjxmQQgHiSGDA4QIxBEhIEuQgyD4gZHOQh/LZiSAAQiAAAiRo6g",
      "transform": {
        "x": 739.1,
        "y": 209.7
      },
      "color": "#000000"
    },
    {
      "strokeNumber": 15,
      "segment": 2,
      "frame": 363,
      "pathData": "Ai+NZIAAyHQgHrujxmQQgHiSGDA4QIxBEhIEuQgyD4gZHPQgcIKADMcIAAE2QiAGIhyAAQiXAAiAq+g",
      "transform": {
        "x": 739.1,
        "y": 274.3
      },
      "color": "#000000"
    },
    {
      "strokeNumber": 15,
      "segment": 3,
      "frame": 366,
      "pathData": "Ai+bqMAAAgrAQgHrujxmQQgHiSGDA4QIxBEhIEuQgyD4gZHPQgcILADMbIAATkQioMqiRAAQhuAAhinVg",
      "transform": {
        "x": 739.1,
        "y": 342.3
      },
      "color": "#000000"
    },
    {
      "strokeNumber": 15,
      "segment": 4,
      "frame": 369,
      "pathData": "Ai+dPMAAAg6rQgHrujxmRQgHiSGDA4QIxBFhIEtQgyD4gZHQQgcIKADMcMAAAA1dQiLG9hrAAQi1AAhez2g",
      "transform": {
        "x": 739.1,
        "y": 432.6
      },
      "color": "#000000"
    },
    {
      "strokeNumber": 15,
      "segment": 5,
      "frame": 372,
      "pathData": "EgBEA5XQipjtAvxRMAAAhKWQgHrujxmRQgHiSGDA4QIxBFhIEtQgyD5gZHPQgcIKADMcMAAAA1dQilX/jDAAQgTAAgUgPg",
      "transform": {
        "x": 739.1,
        "y": 487.1
      },
      "color": "#000000"
    },
    {
      "strokeNumber": 16,
      "segment": 1,
      "frame": 384,
      "pathData": "AiWCIQhPiQhHimQgii2IBDyQDnFvjHAAQhwAAj5h1g",
      "transform": {
        "x": 449.2,
        "y": 399.5
      },
      "color": "#000000"
    },
    {
      "strokeNumber": 16,
      "segment": 2,
      "frame": 387,
      "pathData": "ACaHfQj1jljCleQhPiRhHimQgii3IBDzQFOCGA4EAQAgHDjmAAQglAAgtgLg",
      "transform": {
        "x": 462.7,
        "y": 423.2
      },
      "color": "#000000"
    },
    {
      "strokeNumber": 17,
      "segment": 1,
      "frame": 408,
      "pathData": "AptCRQK/iVGClAQG2EwraDrQgRAFgVAHIAAAAQkaBfjtADQktg0A9iAg",
      "transform": {
        "x": 467.3,
        "y": 576.6
      },
      "color": "#000000"
    },
    {
      "strokeNumber": 17,
      "segment": 2,
      "frame": 411,
      "pathData": "AAwE+QCHlGjYA4QgSAFgUAHIAAAAQkcBfjtADQksg0A8h/QLBiWGBlAQCugxE8EhQDgCVkwDcQlFF9ieAAQhsAAgdi1g",
      "transform": {
        "x": 488.4,
        "y": 593.3
      },
      "color": "#000000"
    },
    {
      "strokeNumber": 17,
      "segment": 3,
      "frame": 414,
      "pathData": "AiNJiIC9oIQCHlGjYA6QgSAEgUAIIAAAAQkcBfjtACQksgzA8iBQLBiVGBlBQCugxE8EhQDgCVkwDdIpsMBQhTBDgvAAQg+AAADh1g",
      "transform": {
        "x": 488.4,
        "y": 616.1
      },
      "color": "#000000"
    },
    {
      "strokeNumber": 18,
      "segment": 1,
      "frame": 432,
      "pathData": "AhUAQIkEmsQEWhcGbJ4QgJEohcAAQhsAAjcmYg",
      "transform": {
        "x": 508.7,
        "y": 718.4
      },
      "color": "#000000"
    },
    {
      "strokeNumber": 18,
      "segment": 2,
      "frame": 435,
      "pathData": "Ah3mGIkEmtQEXhcGaJ5QDALElWEtIiCBkQB3pBkMqEg",
      "transform": {
        "x": 512.1,
        "y": 759.1
      },
      "color": "#000000"
    },
    {
      "strokeNumber": 19,
      "segment": 1,
      "frame": 456,
      "pathData": "Ao3DTQmMk0BMi1IQkAAQVbC0y/CzIgnAFQjpAhjzBSQhrBOhiAAQhcAAhUhEg",
      "transform": {
        "x": 456.9,
        "y": 851.1
      },
      "color": "#000000"
    },
    {
      "strokeNumber": 19,
      "segment": 2,
      "frame": 459,
      "pathData": "AKFCwQockNpgBKIgnAFQjpAgj0BSQjPCViuiLQmMk0BMi1IQlAAQKCgxGDBjQJ7DrKpCJQCYFhlXAAQkOAApEjcg",
      "transform": {
        "x": 540.2,
        "y": 861.2
      },
      "color": "#000000"
    },
    {
      "strokeNumber": 19,
      "segment": 3,
      "frame": 462,
      "pathData": "ASqHMIzVnyQockOphBKIgnAFQjqAhjzBSQjPCUiuiKQmMk1BMi1IQlAAQKBgyGFBkQJ6DrKpCKQJEB2JmAxQKsG/0+CoQifhEi0hTg",
      "transform": {
        "x": 609.1,
        "y": 882.7
      },
      "color": "#000000"
    },
    {
      "strokeNumber": 19,
      "segment": 4,
      "frame": 465,
      "pathData": "AJUHEQifhFi0hTIzWnyQobkOphBKIgoAFQjpAhj0BSQjOCWiuiMQmMk1BMi1IQkAAQKCgxGEBjQJ8DrKoCKQJEB2JlAxQEpAXEwAHIXhBBQhsE33kIBQgrAQhCAAQkmAArok/g",
      "transform": {
        "x": 702.8,
        "y": 898.7
      },
      "color": "#000000"
    }
  ],
  "inLexicalListsHK": true,
  "stage1Words": [],
  "stage2Words": [
    {
      "word": "項鏈",
      "jyutping": "hong6lin6",
      "pinyin": "xiɑ̀ngliɑ̀n",
      "stage": "2"
    },
    {
      "word": "頸鏈",
      "jyutping": "geng2lin6",
      "pinyin": "jǐng liɑ̀n",
      "stage": "2"
    }
  ],
  "fourCharacterPhrases": [],
  "classicalPhrases": [],
  "multiCharacterIdioms": [],
  "properNouns": [],
  "transliteratedWords": []
}